softchat/__init__.py
softchat/__main__.py
softchat/ass.py
softchat/fconv.py
softchat/fff.py
softchat/mproc.py
softchat/the_test.py
softchat/util.py
softchat-1.8.dist-info/LICENSE
softchat-1.8.dist-info/METADATA
softchat-1.8.dist-info/WHEEL
softchat-1.8.dist-info/entry_points.txt
softchat-1.8.dist-info/top_level.txt
softchat-1.8.dist-info/RECORD
