Metadata-Version: 2.1
Name: softchat
Version: 1.8
Summary: convert twitch/youtube chat into softsubs
Home-page: https://github.com/9001/softchat
Author: ed
Author-email: softchat@ocv.me
License: MIT
Keywords: youtube chat converter danmaku marquee softsubs ass subtitles
Classifier: License :: OSI Approved :: MIT License
Classifier: Development Status :: 5 - Production/Stable
Classifier: Environment :: Console
Classifier: Operating System :: Microsoft :: Windows
Classifier: Operating System :: POSIX :: Linux
Classifier: Operating System :: MacOS
Classifier: Natural Language :: English
Classifier: Topic :: Multimedia :: Video
Classifier: Intended Audience :: End Users/Desktop
Classifier: Programming Language :: Python :: 3
Classifier: Programming Language :: Python :: 3.6
Classifier: Programming Language :: Python :: 3.7
Classifier: Programming Language :: Python :: 3.8
Classifier: Programming Language :: Python :: 3.9
Classifier: Programming Language :: Python :: 3.10
Classifier: Programming Language :: Python :: 3.11
Classifier: Programming Language :: Python :: 3.12
Classifier: Programming Language :: Python :: 3.13
Requires-Python: >=3.6
License-File: LICENSE
Requires-Dist: Pillow
Requires-Dist: fonttools
Provides-Extra: unkanji
Requires-Dist: fugashi[unidic] ; extra == 'unkanji'
